LICENSE.txt
README.md
setup.cfg
setup.py
SQLLite3HelperClass/SQLLite3HelperClass.py
SQLLite3HelperClass/__init__.py
SQLLite3HelperClass.egg-info/PKG-INFO
SQLLite3HelperClass.egg-info/SOURCES.txt
SQLLite3HelperClass.egg-info/dependency_links.txt
SQLLite3HelperClass.egg-info/top_level.txt