Metadata-Version: 2.1
Name: SQLLite3HelperClass
Version: 0.1.3
Summary: Initializes an sqlite3 database and has a basic query method. This class is meant to be subclassed and expanded.
Home-page: https://github.com/amcsparron2793-Water/SQLLite3HelperClass
Author: Amcsparron
Author-email: amcsparron@albanyny.gov
License: MIT License
Download-URL: https://github.com/amcsparron2793-Water/SQLLite3HelperClass/archive/refs/tags/0.1.3.tar.gz
Keywords: Sqlite3,database
Platform: UNKNOWN
License-File: LICENSE.txt
